LHCbDIRAC/__init__.py
LHCbDIRAC/AccountingSystem/__init__.py
LHCbDIRAC/AccountingSystem/Client/__init__.py
LHCbDIRAC/AccountingSystem/Client/Types/DataStorage.py
LHCbDIRAC/AccountingSystem/Client/Types/JobStep.py
LHCbDIRAC/AccountingSystem/Client/Types/Popularity.py
LHCbDIRAC/AccountingSystem/Client/Types/Storage.py
LHCbDIRAC/AccountingSystem/Client/Types/UserStorage.py
LHCbDIRAC/AccountingSystem/Client/Types/__init__.py
LHCbDIRAC/AccountingSystem/Client/Types/test/Test_AS_Client_Types_DataStorage.py
LHCbDIRAC/AccountingSystem/private/__init__.py
LHCbDIRAC/AccountingSystem/private/Plotters/DataStoragePlotter.py
LHCbDIRAC/AccountingSystem/private/Plotters/JobStepPlotter.py
LHCbDIRAC/AccountingSystem/private/Plotters/PopularityPlotter.py
LHCbDIRAC/AccountingSystem/private/Plotters/StoragePlotter.py
LHCbDIRAC/AccountingSystem/private/Plotters/UserStoragePlotter.py
LHCbDIRAC/AccountingSystem/private/Plotters/__init__.py
LHCbDIRAC/AccountingSystem/private/Plotters/test/Test_AS_private_Plotters_DataStoragePlotter.py
LHCbDIRAC/AccountingSystem/private/Plotters/test/Test_AS_private_Plotters_JobStepPlotter.py
LHCbDIRAC/AccountingSystem/private/Plotters/test/Test_AS_private_Plotters_PopularityPlotter.py
LHCbDIRAC/AccountingSystem/private/Plotters/test/Test_AS_private_Plotters_StoragePlotter.py
LHCbDIRAC/BookkeepingSystem/ConfigTemplate.cfg
LHCbDIRAC/BookkeepingSystem/__init__.py
LHCbDIRAC/BookkeepingSystem/Client/BKQuery.py
LHCbDIRAC/BookkeepingSystem/Client/BookkeepingClient.py
LHCbDIRAC/BookkeepingSystem/Client/Help.py
LHCbDIRAC/BookkeepingSystem/Client/JEncoder.py
LHCbDIRAC/BookkeepingSystem/Client/LHCB_BKKDBClient.py
LHCbDIRAC/BookkeepingSystem/Client/LHCbBookkeepingCLI.py
LHCbDIRAC/BookkeepingSystem/Client/LHCbBookkeepingManager.py
LHCbDIRAC/BookkeepingSystem/Client/ScriptExecutors.py
LHCbDIRAC/BookkeepingSystem/Client/__init__.py
LHCbDIRAC/BookkeepingSystem/Client/objects.py
LHCbDIRAC/BookkeepingSystem/Client/test/Test_BKQuery.py
lhcbdirac-12.0.5.dist-info/METADATA
lhcbdirac-12.0.5.dist-info/WHEEL
lhcbdirac-12.0.5.dist-info/entry_points.txt
lhcbdirac-12.0.5.dist-info/top_level.txt
lhcbdirac-12.0.5.dist-info/RECORD
