Metadata-Version: 2.4
Name: LHCbDIRAC
Version: 12.0.5
Summary: LHCbDIRAC is the LHCb extension of DIRAC
Home-page: https://gitlab.cern.ch/lhcb-dirac/LHCbDIRAC/
License: GPL-3.0-only
Classifier: Development Status :: 5 - Production/Stable
Classifier: Intended Audience :: Science/Research
Classifier: License :: OSI Approved :: GNU General Public License v3 (GPLv3)
Classifier: Programming Language :: Python :: 3
Classifier: Topic :: Scientific/Engineering
Classifier: Topic :: System :: Distributed Computing
Requires-Python: >=3.11
Requires-Dist: DIRAC~=9.0.4
Requires-Dist: LbPlatformUtils>=4.5.0
Requires-Dist: LbEnv>=2.3.0
Requires-Dist: LbProdRun
Requires-Dist: LbCondaWrappers
Requires-Dist: requests
Requires-Dist: pydantic>=2
Requires-Dist: uproot[xrootd]>=5.3
Requires-Dist: pyyaml
Requires-Dist: xmltodict
Requires-Dist: hyperscan
Requires-Dist: levenshtein
Requires-Dist: zstandard
Requires-Dist: rich
Requires-Dist: httpx
Requires-Dist: beautifulsoup4
Requires-Dist: python-gitlab
Requires-Dist: pandas
Requires-Dist: numpy
Requires-Dist: lhcbdiracx-client
Requires-Dist: lhcbdiracx-core
Requires-Dist: lhcbdiracx-cli
Provides-Extra: server
Requires-Dist: oracledb<1.3; extra == "server"
Requires-Dist: DIRAC[server]~=9.0.4; extra == "server"
Requires-Dist: psutil; extra == "server"
Requires-Dist: stomp.py; extra == "server"
Requires-Dist: suds; extra == "server"
Provides-Extra: testing
Requires-Dist: mock; extra == "testing"
Requires-Dist: pytest-mock; extra == "testing"
Requires-Dist: Pillow; extra == "testing"
Requires-Dist: pytest; extra == "testing"
